dnsmanager/__init__.py
dnsmanager/admin.py
dnsmanager/apps.py
dnsmanager/models.py
dnsmanager/urls.py
dnsmanager/views.py
dnsmanager/api/__init__.py
dnsmanager/api/polymorphic_serializer.py
dnsmanager/api/serializers.py
dnsmanager/api/views.py
dnsmanager/locale/fr/LC_MESSAGES/django.mo
dnsmanager/locale/fr/LC_MESSAGES/django.po
dnsmanager/migrations/0001_initial.py
dnsmanager/migrations/__init__.py
dnsmanager/templates/dnsmanager/zone_detail.html
django_dnsmanager-0.2.2.dist-info/LICENSE
django_dnsmanager-0.2.2.dist-info/METADATA
django_dnsmanager-0.2.2.dist-info/WHEEL
django_dnsmanager-0.2.2.dist-info/top_level.txt
django_dnsmanager-0.2.2.dist-info/RECORD
