Metadata-Version: 2.1
Name: django-dnsmanager
Version: 0.2.2
Summary: Django app to manage DNS zones
Home-page: https://gitlab.crans.org/nounous/django-dnsmanager
Download-URL: https://gitlab.crans.org/nounous/django-dnsmanager/-/releases
Author: Alexandre Iooss
Author-email: erdnaxe@crans.org
Maintainer: Alexandre Iooss
Maintainer-email: erdnaxe@crans.org
License: BSD
Keywords: django,dns,manager
Classifier: Development Status :: 4 - Beta
Classifier: Environment :: Web Environment
Classifier: Framework :: Django
Classifier: Framework :: Django :: 2.2
Classifier: Framework :: Django :: 3.2
Classifier: Framework :: Django :: 4.1
Classifier: Intended Audience :: Developers
Classifier: License :: OSI Approved :: BSD License
Classifier: Operating System :: OS Independent
Classifier: Programming Language :: Python :: 3.7
Classifier: Programming Language :: Python :: 3.8
Classifier: Programming Language :: Python :: 3.9
Classifier: Programming Language :: Python :: 3.10
Classifier: Programming Language :: Python :: 3.11
Classifier: Topic :: Database
License-File: LICENSE
Requires-Dist: Django (<5.0,>=2.2)
Requires-Dist: django-polymorphic (~=3.0)
